{
  "sitecore": {
    "context": {
      "pageEditing": false,
      "site": {
        "name": "rolex-org"
      },
      "pageState": "normal",
      "language": "en",
      "wa": {
        "contentTag": "visual-arts",
        "pageType": "video page",
        "pageSiteSection": "rolex-mentor-protege",
        "pageSiteSubSection": "video",
        "environmentName": "production",
        "pageName": "rolex-mentor-protege:video:visual-arts:david-hockney-and-matthias-weischer",
        "statusCode": "200",
        "environmentVersion": "1.6.18"
      },
      "domain": "https://www.rolex.org",
      "coveo-api-key": "token",
      "coveo-domain-analytics": "https://rolexsaproductionh21l80g7.analytics.org.coveo.com/rest/ua",
      "coveo-domain-platform": "https://rolexsaproductionh21l80g7.org.coveo.com",
      "coveo-pipeline-search": "coveo-prd-rolex-org-cd-web01-search",
      "coveo-pipeline-searchhub": "RolexOrgCDXX",
      "vtts": [],
      "item": {
        "datePublished": "2018-11-29T19:31:35Z",
        "dateModified": "2020-09-18T13:24:52Z"
      }
    },
    "route": {
      "name": "david-hockney-and-matthias-weischer",
      "displayName": "david-hockney-and-matthias-weischer",
      "fields": {
        "pageClass": {
          "value": ""
        },
        "excludeFromSearch": {
          "value": false
        },
        "pageSiteSubSection": {
          "value": "video"
        },
        "pageThumbnail_alt": {
          "value": ""
        },
        "pageTitle": {
          "value": "David Hockney and Matthias Weischer - Video"
        },
        "editorChoice": {
          "value": false
        },
        "menuType": {
          "value": false
        },
        "pageCaption": {
          "value": "“I’ve never done any teaching,” says David Hockney, Britain’s most famous living artist. He agreed to be a mentor in the hope he would not only teach, but also learn. Traveling and painting with his protégé, Germany’s Matthias Weischer, Hockney says, “I’ve got a new friend, a young painter. A good teacher learns from pupils.”"
        },
        "Video": {
          "value": true
        },
        "displayInGrid": {
          "value": true
        },
        "duration": {
          "value": "0min 33s"
        },
        "isHub": {
          "value": false
        },
        "pageThumbnail_src": {
          "value": "/data/media/img/rolex-mentor-protege/visual-arts/2004-2005/david-hockney-and-matthias-weischer/thumbnail.jpg"
        },
        "pageVersion": {
          "value": "dark"
        },
        "Slideshow": {
          "value": false
        },
        "pageType": {
          "id": "dbb52d40-be85-4cf1-98c6-53d5dac6a4ef",
          "url": "/Content/PageType/video-page",
          "fields": {
            "name": {
              "value": ""
            }
          }
        },
        "WaPageTitle": {
          "value": "David Hockney and Matthias Weischer - Video"
        },
        "metadescription": {
          "value": "“I’ve never done any teaching,” says David Hockney, Britain’s most famous living artist. He agreed to be a mentor in the hope he would not only teach, but also learn. Traveling and painting with his protégé, Germany’s Matthias Weischer, Hockney says, “I’ve got a new friend, a young painter. A good teacher learns from pupils.”"
        },
        "backgroundImage": {
          "value": ""
        },
        "backgroundImageMobile": {
          "value": ""
        },
        "backgroundColor": {
          "value": ""
        },
        "pageSiteSection": {
          "value": "rolex-mentor-protege"
        },
        "tag5": null,
        "tag5_ranking": {
          "value": ""
        },
        "hub": {
          "id": "394051ff-bb22-583b-b0a0-7caa7c32000e",
          "url": "/Content/Hub/rolex-mentor-protege",
          "fields": {
            "name": {
              "value": "rolex-mentor-protege"
            },
            "dictionaryKey": {
              "value": "rolex-mentor-protege"
            },
            "url": {
              "value": "rolex-mentor-protege"
            }
          }
        },
        "tag1": {
          "id": "0e5c1e98-a926-5d2c-8eb4-68af189cb7b5",
          "url": "/Content/Category/Visual-Arts",
          "fields": {
            "name": {
              "value": "Visual Arts"
            },
            "dictionaryKey": {
              "value": "visual-arts"
            }
          }
        },
        "tag1_ranking": {
          "value": "1040"
        },
        "tag2": null,
        "tag2_ranking": {
          "value": ""
        },
        "tag3": null,
        "tag4_ranking": {
          "value": ""
        },
        "tag3_ranking": {
          "value": ""
        },
        "tag4": null,
        "hub2": {
          "id": "1b35edcd-f667-5a22-a621-8663f6b9dfa3",
          "url": "/Content/Hub/arts",
          "fields": {
            "name": {
              "value": "arts"
            },
            "dictionaryKey": {
              "value": "all-arts"
            },
            "url": {
              "value": "arts"
            }
          }
        },
        "tag_video": {
          "id": "0e5c1e98-a926-5d2c-8eb4-68af189cb7b5",
          "url": "/Content/Category/Visual-Arts",
          "fields": {
            "name": {
              "value": "Visual Arts"
            },
            "dictionaryKey": {
              "value": "visual-arts"
            }
          }
        },
        "hub_minisite": null,
        "video_timeToWatch": {
          "value": "04:51"
        },
        "previewTitle": {
          "value": "David Hockney and Matthias Weischer - Video"
        },
        "previewImage_src": {
          "value": "/data/media/img/rolex-mentor-protege/visual-arts/2004-2005/david-hockney-and-matthias-weischer/thumbnail.jpg"
        },
        "previewImageCustom_src": {
          "value": ""
        },
        "previewCategory": {
          "value": "Visual Arts"
        },
        "isLink": {
          "value": true
        },
        "customLink": {
          "value": ""
        },
        "isReplay": {
          "value": false
        },
        "isYoutubeStreaming": {
          "value": false
        },
        "gridExternalLinkLabel": {
          "value": ""
        },
        "gridExternalLinkUrl": {
          "value": ""
        },
        "gridExternalLinkWaName": {
          "value": ""
        }
      },
      "databaseName": "web01",
      "deviceId": "fe5d7fdf-89c0-4d99-9aa3-b5fbd009c9f3",
      "itemId": "cf396632-32de-5bc4-9345-16da25476e7b",
      "itemLanguage": "en",
      "itemVersion": 1,
      "layoutId": "de29a1c6-fd50-5ef3-87fc-9dc20cfd4b2e",
      "templateId": "b694dda9-f716-56a8-9d1a-b1b2d74f7d82",
      "templateName": "App Route",
      "placeholders": {
        "layout-placeholder": [
          {
            "uid": "2b1e11c8-7a11-5fb2-8a0f-067abe81e64a",
            "componentName": "Layout",
            "dataSource": "{E9FDCB71-E67B-5CD3-ADC7-634C726F9462}",
            "params": {},
            "fields": {},
            "placeholders": {
              "jss-main": [
                {
                  "uid": "8d785ba1-31d6-5de7-a52c-eb1995838fbf",
                  "componentName": "VideoPlaylist",
                  "dataSource": "{6F728609-8746-5404-BD29-7E8CF65BC66C}",
                  "params": {},
                  "fields": {
                    "video_src": {
                      "value": "/data/media/video/rolex-mentor-protege/visual-arts/2004-2005/david-hockney-and-matthias-weischer/david-hockney-and-matthias-weischer_video_0001.mp4"
                    },
                    "date": {
                      "value": "May 28, 2015"
                    },
                    "description": {
                      "value": "Rolex Mentor and Protégé in Visual Arts, 2004 - 2005"
                    },
                    "poster_alt": {
                      "value": ""
                    },
                    "poster_src": {
                      "value": "/data/media/img/rolex-mentor-protege/visual-arts/2004-2005/david-hockney-and-matthias-weischer/david_hockney_matthias_weischer_cover_desktop.jpg"
                    },
                    "title": {
                      "value": "David Hockney and Matthias Weischer"
                    },
                    "video_description": {
                      "value": ""
                    },
                    "us_text": {
                      "value": ""
                    },
                    "us_video_src": {
                      "value": ""
                    },
                    "link": {
                      "value": "/rolex-mentor-protege/visual-arts/one-wish"
                    },
                    "text": {
                      "value": "“I’ve never done any teaching,” says David Hockney, Britain’s most famous living artist. He agreed to be a mentor in the hope he would not only teach, but also learn. Traveling and painting with his protégé, Germany’s Matthias Weischer, Hockney says, “I’ve got a new friend, a young painter. A good teacher learns from pupils.”"
                    },
                    "time": {
                      "value": "04:51"
                    },
                    "video_title": {
                      "value": ""
                    },
                    "__Presets": [],
                    "__Facets": [],
                    "__Enabled Views": [],
                    "__Quick Actions": [],
                    "related_videos": [
                      {
                        "name": "olafur-eliasson-and-sammy-baloji",
                        "id": "400354a7a19c54e7a42f65043ee4b5a4",
                        "url": "/rolex-mentor-protege/video/visual-arts/olafur-eliasson-and-sammy-baloji",
                        "fields": {
                          "pageClass": {
                            "value": ""
                          },
                          "excludeFromSearch": {
                            "value": false
                          },
                          "pageSiteSubSection": {
                            "value": "video"
                          },
                          "pageThumbnail_alt": {
                            "value": ""
                          },
                          "pageTitle": {
                            "value": "Olafur Eliasson and Sammy Baloji - Video"
                          },
                          "editorChoice": {
                            "value": false
                          },
                          "menuType": {
                            "value": false
                          },
                          "pageCaption": {
                            "value": "For Sammy Baloji, who had mainly worked in photography, immersion in the life and work of mentor and multimedia artist Olafur Eliasson brought a transformation, enriching his work and bringing a greater complexity of language as he discovered new materials and modes of expression."
                          },
                          "Video": {
                            "value": true
                          },
                          "displayInGrid": {
                            "value": true
                          },
                          "duration": {
                            "value": ""
                          },
                          "isHub": {
                            "value": false
                          },
                          "pageThumbnail_src": {
                            "value": "/data/media/img/rolex-mentor-protege/visual-arts/2014-2015/olafur-eliasson-and-sammy-baloji/thumbnail.jpg"
                          },
                          "pageVersion": {
                            "value": "dark"
                          },
                          "Slideshow": {
                            "value": false
                          },
                          "pageType": {
                            "id": "dbb52d40-be85-4cf1-98c6-53d5dac6a4ef",
                            "url": "/Content/PageType/video-page",
                            "fields": {
                              "name": {
                                "value": ""
                              }
                            }
                          },
                          "WaPageTitle": {
                            "value": "Olafur Eliasson and Sammy Baloji - Video"
                          },
                          "metadescription": {
                            "value": "For Sammy Baloji, who had mainly worked in photography, immersion in the life and work of mentor and multimedia artist Olafur Eliasson brought a transformation, enriching his work and bringing a greater complexity of language as he discovered new materials and modes of expression."
                          },
                          "backgroundImage": {
                            "value": ""
                          },
                          "backgroundImageMobile": {
                            "value": ""
                          },
                          "backgroundColor": {
                            "value": ""
                          },
                          "pageSiteSection": {
                            "value": "rolex-mentor-protege"
                          },
                          "tag5": null,
                          "tag5_ranking": {
                            "value": ""
                          },
                          "hub": {
                            "id": "394051ff-bb22-583b-b0a0-7caa7c32000e",
                            "url": "/Content/Hub/rolex-mentor-protege",
                            "fields": {
                              "name": {
                                "value": "rolex-mentor-protege"
                              },
                              "dictionaryKey": {
                                "value": "rolex-mentor-protege"
                              },
                              "url": {
                                "value": "rolex-mentor-protege"
                              }
                            }
                          },
                          "tag1": {
                            "id": "0e5c1e98-a926-5d2c-8eb4-68af189cb7b5",
                            "url": "/Content/Category/Visual-Arts",
                            "fields": {
                              "name": {
                                "value": "Visual Arts"
                              },
                              "dictionaryKey": {
                                "value": "visual-arts"
                              }
                            }
                          },
                          "tag1_ranking": {
                            "value": "1400"
                          },
                          "tag2": null,
                          "tag2_ranking": {
                            "value": ""
                          },
                          "tag3": null,
                          "tag4_ranking": {
                            "value": ""
                          },
                          "tag3_ranking": {
                            "value": ""
                          },
                          "tag4": null,
                          "hub2": {
                            "id": "1b35edcd-f667-5a22-a621-8663f6b9dfa3",
                            "url": "/Content/Hub/arts",
                            "fields": {
                              "name": {
                                "value": "arts"
                              },
                              "dictionaryKey": {
                                "value": "all-arts"
                              },
                              "url": {
                                "value": "arts"
                              }
                            }
                          },
                          "tag_video": {
                            "id": "0e5c1e98-a926-5d2c-8eb4-68af189cb7b5",
                            "url": "/Content/Category/Visual-Arts",
                            "fields": {
                              "name": {
                                "value": "Visual Arts"
                              },
                              "dictionaryKey": {
                                "value": "visual-arts"
                              }
                            }
                          },
                          "hub_minisite": null,
                          "video_timeToWatch": {
                            "value": "03:09"
                          },
                          "previewTitle": {
                            "value": "Olafur Eliasson and Sammy Baloji - Video"
                          },
                          "previewImage_src": {
                            "value": "/data/media/img/rolex-mentor-protege/visual-arts/2014-2015/olafur-eliasson-and-sammy-baloji/thumbnail.jpg"
                          },
                          "previewImageCustom_src": {
                            "value": ""
                          },
                          "previewCategory": {
                            "value": "Visual Arts"
                          },
                          "isLink": {
                            "value": true
                          },
                          "customLink": {
                            "value": ""
                          },
                          "isReplay": {
                            "value": false
                          },
                          "isYoutubeStreaming": {
                            "value": false
                          },
                          "gridExternalLinkLabel": {
                            "value": ""
                          },
                          "gridExternalLinkUrl": {
                            "value": ""
                          },
                          "gridExternalLinkWaName": {
                            "value": ""
                          }
                        }
                      },
                      {
                        "name": "joan-jonas-and-thao-nguyen-phan",
                        "id": "716dbf06b1a050089618c224a4aa57c5",
                        "url": "/rolex-mentor-protege/video/visual-arts/joan-jonas-and-thao-nguyen-phan",
                        "fields": {
                          "pageClass": {
                            "value": ""
                          },
                          "excludeFromSearch": {
                            "value": false
                          },
                          "pageSiteSubSection": {
                            "value": "video"
                          },
                          "pageThumbnail_alt": {
                            "value": ""
                          },
                          "pageTitle": {
                            "value": "Joan Jonas and Thao Nguyen Phan - Video"
                          },
                          "editorChoice": {
                            "value": false
                          },
                          "menuType": {
                            "value": false
                          },
                          "pageCaption": {
                            "value": "“Art is a spiritual practice,” says Joan Jonas, pioneer of performance and video art. For her Vietnamese protégée Thao Nguyen Phan, the experience of working with Jonas and observing her constant experimentation has taught her to be more open to what she can use to tell the stories that underlie her work."
                          },
                          "Video": {
                            "value": true
                          },
                          "displayInGrid": {
                            "value": false
                          },
                          "duration": {
                            "value": "0min 29s"
                          },
                          "isHub": {
                            "value": false
                          },
                          "pageThumbnail_src": {
                            "value": "/data/media/img/rolex-mentor-protege/visual-arts/2016-2017/joan-jonas_thao-nguyen-phan/thumbnail.jpg"
                          },
                          "pageVersion": {
                            "value": "dark"
                          },
                          "Slideshow": {
                            "value": false
                          },
                          "pageType": {
                            "id": "dbb52d40-be85-4cf1-98c6-53d5dac6a4ef",
                            "url": "/Content/PageType/video-page",
                            "fields": {
                              "name": {
                                "value": ""
                              }
                            }
                          },
                          "WaPageTitle": {
                            "value": "Joan Jonas and Thao Nguyen Phan - Video"
                          },
                          "metadescription": {
                            "value": "“Art is a spiritual practice,” says Joan Jonas, pioneer of performance and video art. For her Vietnamese protégée Thao Nguyen Phan, the experience of working with Jonas and observing her constant experimentation has taught her to be more open to what she can use to tell the stories that underlie her work."
                          },
                          "backgroundImage": {
                            "value": ""
                          },
                          "backgroundImageMobile": {
                            "value": ""
                          },
                          "backgroundColor": {
                            "value": ""
                          },
                          "pageSiteSection": {
                            "value": "rolex-mentor-protege"
                          },
                          "tag5": null,
                          "tag5_ranking": {
                            "value": ""
                          },
                          "hub": {
                            "id": "394051ff-bb22-583b-b0a0-7caa7c32000e",
                            "url": "/Content/Hub/rolex-mentor-protege",
                            "fields": {
                              "name": {
                                "value": "rolex-mentor-protege"
                              },
                              "dictionaryKey": {
                                "value": "rolex-mentor-protege"
                              },
                              "url": {
                                "value": "rolex-mentor-protege"
                              }
                            }
                          },
                          "tag1": {
                            "id": "0e5c1e98-a926-5d2c-8eb4-68af189cb7b5",
                            "url": "/Content/Category/Visual-Arts",
                            "fields": {
                              "name": {
                                "value": "Visual Arts"
                              },
                              "dictionaryKey": {
                                "value": "visual-arts"
                              }
                            }
                          },
                          "tag1_ranking": {
                            "value": "1800"
                          },
                          "tag2": null,
                          "tag2_ranking": {
                            "value": ""
                          },
                          "tag3": null,
                          "tag4_ranking": {
                            "value": ""
                          },
                          "tag3_ranking": {
                            "value": ""
                          },
                          "tag4": null,
                          "hub2": {
                            "id": "1b35edcd-f667-5a22-a621-8663f6b9dfa3",
                            "url": "/Content/Hub/arts",
                            "fields": {
                              "name": {
                                "value": "arts"
                              },
                              "dictionaryKey": {
                                "value": "all-arts"
                              },
                              "url": {
                                "value": "arts"
                              }
                            }
                          },
                          "tag_video": {
                            "id": "0e5c1e98-a926-5d2c-8eb4-68af189cb7b5",
                            "url": "/Content/Category/Visual-Arts",
                            "fields": {
                              "name": {
                                "value": "Visual Arts"
                              },
                              "dictionaryKey": {
                                "value": "visual-arts"
                              }
                            }
                          },
                          "hub_minisite": null,
                          "video_timeToWatch": {
                            "value": "03:42"
                          },
                          "previewTitle": {
                            "value": "Joan Jonas and Thao Nguyen Phan - Video"
                          },
                          "previewImage_src": {
                            "value": "/data/media/img/rolex-mentor-protege/visual-arts/2016-2017/joan-jonas_thao-nguyen-phan/thumbnail.jpg"
                          },
                          "previewImageCustom_src": {
                            "value": ""
                          },
                          "previewCategory": {
                            "value": "Visual Arts"
                          },
                          "isLink": {
                            "value": true
                          },
                          "customLink": {
                            "value": ""
                          },
                          "isReplay": {
                            "value": false
                          },
                          "isYoutubeStreaming": {
                            "value": false
                          },
                          "gridExternalLinkLabel": {
                            "value": ""
                          },
                          "gridExternalLinkUrl": {
                            "value": ""
                          },
                          "gridExternalLinkWaName": {
                            "value": ""
                          }
                        }
                      },
                      {
                        "name": "rebecca-horn-and-masanori-handa",
                        "id": "b573ae0915dc50e6a529e98cc584ec63",
                        "url": "/rolex-mentor-protege/video/visual-arts/rebecca-horn-and-masanori-handa",
                        "fields": {
                          "pageClass": {
                            "value": ""
                          },
                          "excludeFromSearch": {
                            "value": false
                          },
                          "pageSiteSubSection": {
                            "value": "video"
                          },
                          "pageThumbnail_alt": {
                            "value": ""
                          },
                          "pageTitle": {
                            "value": "Rebecca Horn and Masanori Handa - Video"
                          },
                          "editorChoice": {
                            "value": false
                          },
                          "menuType": {
                            "value": false
                          },
                          "pageCaption": {
                            "value": "Two enigmatic visual artists, Rebecca Horn and Masanori Handa, from very different countries, Germany and Japan, quickly develop a strong friendship and a mutual admiration for each other’s category-defying work. Communication during their mentorship is not confined to language – drawing together enables them to boost their joint creativity."
                          },
                          "Video": {
                            "value": true
                          },
                          "displayInGrid": {
                            "value": true
                          },
                          "duration": {
                            "value": "0min 29s"
                          },
                          "isHub": {
                            "value": false
                          },
                          "pageThumbnail_src": {
                            "value": "/data/media/img/rolex-mentor-protege/visual-arts/2008-2009/rebecca-horn-and-masanori-handa/thumbnail.jpg"
                          },
                          "pageVersion": {
                            "value": "dark"
                          },
                          "Slideshow": {
                            "value": false
                          },
                          "pageType": {
                            "id": "dbb52d40-be85-4cf1-98c6-53d5dac6a4ef",
                            "url": "/Content/PageType/video-page",
                            "fields": {
                              "name": {
                                "value": ""
                              }
                            }
                          },
                          "WaPageTitle": {
                            "value": "Rebecca Horn and Masanori Handa - Video"
                          },
                          "metadescription": {
                            "value": "Two enigmatic visual artists, Rebecca Horn and Masanori Handa, from very different countries, Germany and Japan, quickly develop a strong friendship and a mutual admiration for each other’s category-defying work. Communication during their mentorship is not confined to language – drawing together enables them to boost their joint creativity."
                          },
                          "backgroundImage": {
                            "value": ""
                          },
                          "backgroundImageMobile": {
                            "value": ""
                          },
                          "backgroundColor": {
                            "value": ""
                          },
                          "pageSiteSection": {
                            "value": "rolex-mentor-protege"
                          },
                          "tag5": null,
                          "tag5_ranking": {
                            "value": ""
                          },
                          "hub": {
                            "id": "394051ff-bb22-583b-b0a0-7caa7c32000e",
                            "url": "/Content/Hub/rolex-mentor-protege",
                            "fields": {
                              "name": {
                                "value": "rolex-mentor-protege"
                              },
                              "dictionaryKey": {
                                "value": "rolex-mentor-protege"
                              },
                              "url": {
                                "value": "rolex-mentor-protege"
                              }
                            }
                          },
                          "tag1": {
                            "id": "0e5c1e98-a926-5d2c-8eb4-68af189cb7b5",
                            "url": "/Content/Category/Visual-Arts",
                            "fields": {
                              "name": {
                                "value": "Visual Arts"
                              },
                              "dictionaryKey": {
                                "value": "visual-arts"
                              }
                            }
                          },
                          "tag1_ranking": {
                            "value": "150"
                          },
                          "tag2": null,
                          "tag2_ranking": {
                            "value": ""
                          },
                          "tag3": null,
                          "tag4_ranking": {
                            "value": ""
                          },
                          "tag3_ranking": {
                            "value": ""
                          },
                          "tag4": null,
                          "hub2": {
                            "id": "1b35edcd-f667-5a22-a621-8663f6b9dfa3",
                            "url": "/Content/Hub/arts",
                            "fields": {
                              "name": {
                                "value": "arts"
                              },
                              "dictionaryKey": {
                                "value": "all-arts"
                              },
                              "url": {
                                "value": "arts"
                              }
                            }
                          },
                          "tag_video": {
                            "id": "0e5c1e98-a926-5d2c-8eb4-68af189cb7b5",
                            "url": "/Content/Category/Visual-Arts",
                            "fields": {
                              "name": {
                                "value": "Visual Arts"
                              },
                              "dictionaryKey": {
                                "value": "visual-arts"
                              }
                            }
                          },
                          "hub_minisite": null,
                          "video_timeToWatch": {
                            "value": "04:09"
                          },
                          "previewTitle": {
                            "value": "Rebecca Horn and Masanori Handa - Video"
                          },
                          "previewImage_src": {
                            "value": "/data/media/img/rolex-mentor-protege/visual-arts/2008-2009/rebecca-horn-and-masanori-handa/thumbnail.jpg"
                          },
                          "previewImageCustom_src": {
                            "value": ""
                          },
                          "previewCategory": {
                            "value": "Visual Arts"
                          },
                          "isLink": {
                            "value": true
                          },
                          "customLink": {
                            "value": ""
                          },
                          "isReplay": {
                            "value": false
                          },
                          "isYoutubeStreaming": {
                            "value": false
                          },
                          "gridExternalLinkLabel": {
                            "value": ""
                          },
                          "gridExternalLinkUrl": {
                            "value": ""
                          },
                          "gridExternalLinkWaName": {
                            "value": ""
                          }
                        }
                      }
                    ]
                  },
                  "placeholders": {
                    "jss-related-videos": [
                      {
                        "uid": "4e75d764-7a65-4af0-ad74-70a16feb2978",
                        "componentName": "RelatedItems",
                        "dataSource": "{233E1D5A-A2EF-4905-9213-5D4880A339C0}",
                        "params": {},
                        "fields": {
                          "title": {
                            "value": "Discover our related videos"
                          },
                          "relatedItems": [
                            {
                              "id": "f8f49402-aed2-5ecd-817b-4c598f0b9c81",
                              "fields": {
                                "pageClass": {
                                  "value": ""
                                },
                                "excludeFromSearch": {
                                  "value": false
                                },
                                "pageSiteSubSection": {
                                  "value": "video"
                                },
                                "pageThumbnail_alt": {
                                  "value": ""
                                },
                                "pageTitle": {
                                  "value": "Álvaro Siza & Sahel Alhiyari - Video"
                                },
                                "editorChoice": {
                                  "value": false
                                },
                                "menuType": {
                                  "value": false
                                },
                                "pageCaption": {
                                  "value": "For &Aacute;lvaro Siza, Portugal&rsquo;s master architect, his profession is not about copying designs of the past. His prot&eacute;g&eacute;, Sahel Alhiyari, says &ldquo;with Siza &hellip; it&rsquo;s much deeper than that.&rdquo; Alhiyari&nbsp;explains that &ldquo;architecture is synonymous with human existence. It&rsquo;s one&rsquo;s second skin.&rdquo;"
                                },
                                "Video": {
                                  "value": true
                                },
                                "displayInGrid": {
                                  "value": true
                                },
                                "duration": {
                                  "value": "0min 26s"
                                },
                                "isHub": {
                                  "value": false
                                },
                                "pageThumbnail_src": {
                                  "value": "/data/media/img/rolex-mentor-protege/visual-arts/2002-2003/alvaro-siza-and-sahel-al-hiyari/thumbnail.jpg"
                                },
                                "pageVersion": {
                                  "value": "dark"
                                },
                                "Slideshow": {
                                  "value": false
                                },
                                "pageType": {
                                  "id": "dbb52d40-be85-4cf1-98c6-53d5dac6a4ef",
                                  "url": "/Content/PageType/video-page",
                                  "fields": {
                                    "name": {
                                      "value": ""
                                    }
                                  }
                                },
                                "WaPageTitle": {
                                  "value": "Álvaro Siza & Sahel Alhiyari - Video"
                                },
                                "metadescription": {
                                  "value": "For &Aacute;lvaro Siza, Portugal&rsquo;s master architect, his profession is not about copying designs of the past. His prot&eacute;g&eacute;, Sahel Alhiyari, says &ldquo;with Siza &hellip; it&rsquo;s much deeper than that.&rdquo; Alhiyari&nbsp;explains that &ldquo;architecture is synonymous with human existence. It&rsquo;s one&rsquo;s second skin.&rdquo;"
                                },
                                "backgroundImage": {
                                  "value": ""
                                },
                                "backgroundImageMobile": {
                                  "value": ""
                                },
                                "backgroundColor": {
                                  "value": ""
                                },
                                "pageSiteSection": {
                                  "value": "rolex-mentor-protege"
                                },
                                "tag5": null,
                                "tag5_ranking": {
                                  "value": ""
                                },
                                "hub": {
                                  "id": "394051ff-bb22-583b-b0a0-7caa7c32000e",
                                  "url": "/Content/Hub/rolex-mentor-protege",
                                  "fields": {
                                    "name": {
                                      "value": "rolex-mentor-protege"
                                    },
                                    "dictionaryKey": {
                                      "value": "rolex-mentor-protege"
                                    },
                                    "url": {
                                      "value": "rolex-mentor-protege"
                                    }
                                  }
                                },
                                "tag1": {
                                  "id": "3ffae34a-278a-5f34-b891-aaff80f4f4b3",
                                  "url": "/Content/Category/Architecture",
                                  "fields": {
                                    "name": {
                                      "value": "Architecture"
                                    },
                                    "dictionaryKey": {
                                      "value": "architecture"
                                    }
                                  }
                                },
                                "tag1_ranking": {
                                  "value": "100"
                                },
                                "tag2": null,
                                "tag2_ranking": {
                                  "value": ""
                                },
                                "tag3": null,
                                "tag4_ranking": {
                                  "value": ""
                                },
                                "tag3_ranking": {
                                  "value": ""
                                },
                                "tag4": null,
                                "hub2": {
                                  "id": "1b35edcd-f667-5a22-a621-8663f6b9dfa3",
                                  "url": "/Content/Hub/arts",
                                  "fields": {
                                    "name": {
                                      "value": "arts"
                                    },
                                    "dictionaryKey": {
                                      "value": "all-arts"
                                    },
                                    "url": {
                                      "value": "arts"
                                    }
                                  }
                                },
                                "tag_video": {
                                  "id": "0e5c1e98-a926-5d2c-8eb4-68af189cb7b5",
                                  "url": "/Content/Category/Visual-Arts",
                                  "fields": {
                                    "name": {
                                      "value": "Visual Arts"
                                    },
                                    "dictionaryKey": {
                                      "value": "visual-arts"
                                    }
                                  }
                                },
                                "hub_minisite": null,
                                "video_timeToWatch": {
                                  "value": "04:33"
                                },
                                "previewTitle": {
                                  "value": "Álvaro Siza & Sahel Alhiyari - Video"
                                },
                                "previewImage_src": {
                                  "value": "/data/media/img/rolex-mentor-protege/visual-arts/2002-2003/alvaro-siza-and-sahel-al-hiyari/thumbnail.jpg"
                                },
                                "previewImageCustom_src": {
                                  "value": ""
                                },
                                "previewCategory": {
                                  "value": "Visual Arts"
                                },
                                "isLink": {
                                  "value": true
                                },
                                "customLink": {
                                  "value": ""
                                },
                                "isReplay": {
                                  "value": false
                                },
                                "isYoutubeStreaming": {
                                  "value": false
                                },
                                "gridExternalLinkLabel": {
                                  "value": ""
                                },
                                "gridExternalLinkUrl": {
                                  "value": ""
                                },
                                "gridExternalLinkWaName": {
                                  "value": ""
                                }
                              }
                            },
                            {
                              "id": "789055ee-63dd-5efb-ba4d-d5c45cb6acb5",
                              "fields": {
                                "pageClass": {
                                  "value": ""
                                },
                                "excludeFromSearch": {
                                  "value": false
                                },
                                "pageSiteSubSection": {
                                  "value": "video"
                                },
                                "pageThumbnail_alt": {
                                  "value": ""
                                },
                                "pageTitle": {
                                  "value": "William Forsythe and Sang Jijia - Video"
                                },
                                "editorChoice": {
                                  "value": false
                                },
                                "menuType": {
                                  "value": false
                                },
                                "pageCaption": {
                                  "value": "William Forsythe, one of the greatest innovators of modern dance, believes that ballet “shouldn’t be left in the 19th century”. His radical approach finds the perfect protégé in Sang Jijia, a gifted Chinese dancer of Tibetan origin. “Sang-ba is like unpolluted water,” says Forsythe. “He runs clear.”"
                                },
                                "Video": {
                                  "value": true
                                },
                                "displayInGrid": {
                                  "value": true
                                },
                                "duration": {
                                  "value": ""
                                },
                                "isHub": {
                                  "value": false
                                },
                                "pageThumbnail_src": {
                                  "value": "/data/media/img/rolex-mentor-protege/dance/2002-2003/william-forsythe-and-sang-jijia/thumbnail.jpg"
                                },
                                "pageVersion": {
                                  "value": "dark"
                                },
                                "Slideshow": {
                                  "value": false
                                },
                                "pageType": {
                                  "id": "dbb52d40-be85-4cf1-98c6-53d5dac6a4ef",
                                  "url": "/Content/PageType/video-page",
                                  "fields": {
                                    "name": {
                                      "value": ""
                                    }
                                  }
                                },
                                "WaPageTitle": {
                                  "value": "William Forsythe and Sang Jijia - Video"
                                },
                                "metadescription": {
                                  "value": "William Forsythe, one of the greatest innovators of modern dance, believes that ballet “shouldn’t be left in the 19th century”. His radical approach finds the perfect protégé in Sang Jijia, a gifted Chinese dancer of Tibetan origin. “Sang-ba is like unpolluted water,” says Forsythe. “He runs clear.”"
                                },
                                "backgroundImage": {
                                  "value": ""
                                },
                                "backgroundImageMobile": {
                                  "value": ""
                                },
                                "backgroundColor": {
                                  "value": ""
                                },
                                "pageSiteSection": {
                                  "value": "rolex-mentor-protege"
                                },
                                "tag5": null,
                                "tag5_ranking": {
                                  "value": ""
                                },
                                "hub": {
                                  "id": "394051ff-bb22-583b-b0a0-7caa7c32000e",
                                  "url": "/Content/Hub/rolex-mentor-protege",
                                  "fields": {
                                    "name": {
                                      "value": "rolex-mentor-protege"
                                    },
                                    "dictionaryKey": {
                                      "value": "rolex-mentor-protege"
                                    },
                                    "url": {
                                      "value": "rolex-mentor-protege"
                                    }
                                  }
                                },
                                "tag1": {
                                  "id": "627221a3-6e58-5177-b459-38b467710232",
                                  "url": "/Content/Category/Dance",
                                  "fields": {
                                    "name": {
                                      "value": "Dance"
                                    },
                                    "dictionaryKey": {
                                      "value": "dance"
                                    }
                                  }
                                },
                                "tag1_ranking": {
                                  "value": "1020"
                                },
                                "tag2": null,
                                "tag2_ranking": {
                                  "value": ""
                                },
                                "tag3": null,
                                "tag4_ranking": {
                                  "value": ""
                                },
                                "tag3_ranking": {
                                  "value": ""
                                },
                                "tag4": null,
                                "hub2": {
                                  "id": "1b35edcd-f667-5a22-a621-8663f6b9dfa3",
                                  "url": "/Content/Hub/arts",
                                  "fields": {
                                    "name": {
                                      "value": "arts"
                                    },
                                    "dictionaryKey": {
                                      "value": "all-arts"
                                    },
                                    "url": {
                                      "value": "arts"
                                    }
                                  }
                                },
                                "tag_video": {
                                  "id": "627221a3-6e58-5177-b459-38b467710232",
                                  "url": "/Content/Category/Dance",
                                  "fields": {
                                    "name": {
                                      "value": "Dance"
                                    },
                                    "dictionaryKey": {
                                      "value": "dance"
                                    }
                                  }
                                },
                                "hub_minisite": null,
                                "video_timeToWatch": {
                                  "value": "05:06"
                                },
                                "previewTitle": {
                                  "value": "William Forsythe and Sang Jijia - Video"
                                },
                                "previewImage_src": {
                                  "value": "/data/media/img/rolex-mentor-protege/dance/2002-2003/william-forsythe-and-sang-jijia/thumbnail.jpg"
                                },
                                "previewImageCustom_src": {
                                  "value": ""
                                },
                                "previewCategory": {
                                  "value": "Dance"
                                },
                                "isLink": {
                                  "value": true
                                },
                                "customLink": {
                                  "value": ""
                                },
                                "isReplay": {
                                  "value": false
                                },
                                "isYoutubeStreaming": {
                                  "value": false
                                },
                                "gridExternalLinkLabel": {
                                  "value": ""
                                },
                                "gridExternalLinkUrl": {
                                  "value": ""
                                },
                                "gridExternalLinkWaName": {
                                  "value": ""
                                }
                              }
                            },
                            {
                              "id": "58ffc0e0-2d40-5016-a254-b9df00e1a4e6",
                              "fields": {
                                "pageClass": {
                                  "value": ""
                                },
                                "excludeFromSearch": {
                                  "value": false
                                },
                                "pageSiteSubSection": {
                                  "value": "video"
                                },
                                "pageThumbnail_alt": {
                                  "value": ""
                                },
                                "pageTitle": {
                                  "value": "Toni Morrison and Julia Leigh - Video"
                                },
                                "editorChoice": {
                                  "value": false
                                },
                                "menuType": {
                                  "value": false
                                },
                                "pageCaption": {
                                  "value": "Nobel literature laureate Toni Morrison is not only a novelist and teacher, she is also an experienced editor – the perfect mentor for young, Australian writer Julia Leigh as she starts on her second novel."
                                },
                                "Video": {
                                  "value": true
                                },
                                "displayInGrid": {
                                  "value": true
                                },
                                "duration": {
                                  "value": ""
                                },
                                "isHub": {
                                  "value": false
                                },
                                "pageThumbnail_src": {
                                  "value": "/data/media/img/rolex-mentor-protege/literature/2002-2003/toni-morrison-and-julia-leigh/thumbnail.jpg"
                                },
                                "pageVersion": {
                                  "value": "dark"
                                },
                                "Slideshow": {
                                  "value": false
                                },
                                "pageType": {
                                  "id": "dbb52d40-be85-4cf1-98c6-53d5dac6a4ef",
                                  "url": "/Content/PageType/video-page",
                                  "fields": {
                                    "name": {
                                      "value": ""
                                    }
                                  }
                                },
                                "WaPageTitle": {
                                  "value": "Toni Morrison and Julia Leigh - Video"
                                },
                                "metadescription": {
                                  "value": "Nobel literature laureate Toni Morrison is not only a novelist and teacher, she is also an experienced editor – the perfect mentor for young, Australian writer Julia Leigh as she starts on her second novel."
                                },
                                "backgroundImage": {
                                  "value": ""
                                },
                                "backgroundImageMobile": {
                                  "value": ""
                                },
                                "backgroundColor": {
                                  "value": ""
                                },
                                "pageSiteSection": {
                                  "value": "rolex-mentor-protege"
                                },
                                "tag5": null,
                                "tag5_ranking": {
                                  "value": ""
                                },
                                "hub": {
                                  "id": "394051ff-bb22-583b-b0a0-7caa7c32000e",
                                  "url": "/Content/Hub/rolex-mentor-protege",
                                  "fields": {
                                    "name": {
                                      "value": "rolex-mentor-protege"
                                    },
                                    "dictionaryKey": {
                                      "value": "rolex-mentor-protege"
                                    },
                                    "url": {
                                      "value": "rolex-mentor-protege"
                                    }
                                  }
                                },
                                "tag1": {
                                  "id": "bdf40ad3-cb16-50a1-8f68-a81e96add59b",
                                  "url": "/Content/Category/Literature",
                                  "fields": {
                                    "name": {
                                      "value": "Literature"
                                    },
                                    "dictionaryKey": {
                                      "value": "literature"
                                    }
                                  }
                                },
                                "tag1_ranking": {
                                  "value": "1020"
                                },
                                "tag2": null,
                                "tag2_ranking": {
                                  "value": ""
                                },
                                "tag3": null,
                                "tag4_ranking": {
                                  "value": ""
                                },
                                "tag3_ranking": {
                                  "value": ""
                                },
                                "tag4": null,
                                "hub2": {
                                  "id": "1b35edcd-f667-5a22-a621-8663f6b9dfa3",
                                  "url": "/Content/Hub/arts",
                                  "fields": {
                                    "name": {
                                      "value": "arts"
                                    },
                                    "dictionaryKey": {
                                      "value": "all-arts"
                                    },
                                    "url": {
                                      "value": "arts"
                                    }
                                  }
                                },
                                "tag_video": {
                                  "id": "bdf40ad3-cb16-50a1-8f68-a81e96add59b",
                                  "url": "/Content/Category/Literature",
                                  "fields": {
                                    "name": {
                                      "value": "Literature"
                                    },
                                    "dictionaryKey": {
                                      "value": "literature"
                                    }
                                  }
                                },
                                "hub_minisite": null,
                                "video_timeToWatch": {
                                  "value": "04:52"
                                },
                                "previewTitle": {
                                  "value": "Toni Morrison and Julia Leigh - Video"
                                },
                                "previewImage_src": {
                                  "value": "/data/media/img/rolex-mentor-protege/literature/2002-2003/toni-morrison-and-julia-leigh/thumbnail.jpg"
                                },
                                "previewImageCustom_src": {
                                  "value": ""
                                },
                                "previewCategory": {
                                  "value": "Literature"
                                },
                                "isLink": {
                                  "value": true
                                },
                                "customLink": {
                                  "value": ""
                                },
                                "isReplay": {
                                  "value": false
                                },
                                "isYoutubeStreaming": {
                                  "value": false
                                },
                                "gridExternalLinkLabel": {
                                  "value": ""
                                },
                                "gridExternalLinkUrl": {
                                  "value": ""
                                },
                                "gridExternalLinkWaName": {
                                  "value": ""
                                }
                              }
                            }
                          ]
                        }
                      }
                    ]
                  }
                }
              ],
              "jss-header": [
                {
                  "uid": "73d34a6e-0bbe-4657-857c-d66761492afa",
                  "componentName": "RolexMenuV2",
                  "dataSource": "",
                  "params": {},
                  "placeholders": {
                    "jss-roller-cards": [
                      {
                        "uid": "2c05b752-7492-46b0-8a4f-2065671bd219",
                        "componentName": "RollerGridLists",
                        "dataSource": "{FD0A956F-6F9A-412A-A5EE-9E4458CB6027}",
                        "params": {
                          "rollerIsMainMenu": "true"
                        },
                        "fields": {
                          "data": {
                            "datasource": {
                              "id": "FD0A956F6F9A412AA5EE9E4458CB6027",
                              "name": "RollerGridLists-Menu",
                              "url": "/en/Components/RollerGridLists/RollerGridLists-Menu",
                              "rollerCardItem": {
                                "value": "{8ACA0347-77BD-49FC-A352-813BB9DE63B5}|{067A57C0-2A11-4D63-AF34-81520A578D4F}|{FA683049-E158-4A5D-9973-CF5CE0D33AA7}|{4F637AC2-2EEF-52CC-A783-13698334026A}|{D9D05BE1-2BED-4148-9E5A-2D594AC08A5E}",
                                "targetItems": [
                                  {
                                    "url": "/en/environment/perpetual-planet/steve-boyes-great-spine-of-africa",
                                    "id": "8ACA034777BD49FCA352813BB9DE63B5",
                                    "name": "steve-boyes-great-spine-of-africa",
                                    "category": {
                                      "value": "Exploration"
                                    },
                                    "title": {
                                      "value": "Protecting our water"
                                    },
                                    "previewImage_src": {
                                      "value": "/data/media/img/environment/perpetual-planet/steve-boyes-great-spine-of-africa/rolex-org-perpetual-planet-steve-boyes-protecting-our-water-thumbnail-article-ppi_rolex_boyes_2507amu_0075_v2_rgb.jpg"
                                    },
                                    "previewImageCustom_src": {
                                      "value": ""
                                    },
                                    "isLink": {
                                      "value": "1"
                                    },
                                    "customLink": {
                                      "value": ""
                                    }
                                  },
                                  {
                                    "url": "/en/environment/perpetual-planet/steve-boyes-cassai-river-expedition",
                                    "id": "067A57C02A114D63AF3481520A578D4F",
                                    "name": "steve-boyes-cassai-river-expedition",
                                    "category": {
                                      "value": "Environment"
                                    },
                                    "title": {
                                      "value": "The Cassai River"
                                    },
                                    "previewImage_src": {
                                      "value": "/data/media/img/environment/perpetual-planet/steve-boyes-cassai-river-expedition/perpetual-planet-steve-boyes-cassai-river-expedition-thumbnail-article-jms7407.jpg"
                                    },
                                    "previewImageCustom_src": {
                                      "value": ""
                                    },
                                    "isLink": {
                                      "value": "1"
                                    },
                                    "customLink": {
                                      "value": ""
                                    }
                                  },
                                  {
                                    "url": "/en/environment/perpetual-planet/steve-boyes-lungwevungu-river-expedition",
                                    "id": "FA683049E1584A5D9973CF5CE0D33AA7",
                                    "name": "steve-boyes-lungwevungu-river-expedition",
                                    "category": {
                                      "value": "Environment"
                                    },
                                    "title": {
                                      "value": "The mighty Zambezi River and its secrets"
                                    },
                                    "previewImage_src": {
                                      "value": "/data/media/img/environment/perpetual-planet/steve-boyes-lungwevungu-river-expedition/rolex-org-environment-steve-boyes-the-mighty-zambezi-river-and-its-secrets-thumbnail-article.jpg"
                                    },
                                    "previewImageCustom_src": {
                                      "value": ""
                                    },
                                    "isLink": {
                                      "value": "1"
                                    },
                                    "customLink": {
                                      "value": ""
                                    }
                                  },
                                  {
                                    "url": "/en/environment/perpetual-planet/okavango-explorer-of-the-year-2019",
                                    "id": "4F637AC22EEF52CCA78313698334026A",
                                    "name": "okavango-explorer-of-the-year-2019",
                                    "category": {
                                      "value": "Environment"
                                    },
                                    "title": {
                                      "value": "The 2019 Rolex National Geographic Explorers of the Year - The Okavango Wilderness Project Team"
                                    },
                                    "previewImage_src": {
                                      "value": "/data/media/img/perpetual-planet/okavango-explorer-of-the-year-2019/thumbnail.jpg"
                                    },
                                    "previewImageCustom_src": {
                                      "value": ""
                                    },
                                    "isLink": {
                                      "value": "1"
                                    },
                                    "customLink": {
                                      "value": ""
                                    }
                                  },
                                  {
                                    "url": "/en/environment/perpetual-planet/fernando-trujillo-explorer-of-the-year-2024",
                                    "id": "D9D05BE12BED41489E5A2D594AC08A5E",
                                    "name": "fernando-trujillo-explorer-of-the-year-2024",
                                    "category": {
                                      "value": "Environment "
                                    },
                                    "title": {
                                      "value": "Fernando Trujillo: For the love of river dolphins"
                                    },
                                    "previewImage_src": {
                                      "value": "/data/media/img/environment/perpetual-planet/fernando-trujillo-explorer-of-the-year-2024/rolex-org-environment-fernando-trujillo-explorer-of-the-year-2024-thumbnail-article.jpg"
                                    },
                                    "previewImageCustom_src": {
                                      "value": ""
                                    },
                                    "isLink": {
                                      "value": "1"
                                    },
                                    "customLink": {
                                      "value": ""
                                    }
                                  }
                                ]
                              }
                            }
                          }
                        }
                      }
                    ]
                  }
                }
              ]
            }
          }
        ]
      }
    }
  },
  "APOLLO_STATE": {},
  "config": {
    "sitecoreApiKey": "809331BB-4AAC-4B95-88AF-8D2F5B522D3C",
    "sitecoreApiHost": "",
    "jssAppName": "rolex-org",
    "defaultLanguage": "en",
    "sitecoreRolexApiHost": "",
    "dbmScript": "//assets.adobedtm.com/7e3b3fa0902e/dd73f31fa358/launch-f98e51ffebe6.min.js",
    "mediaHost": "https://images.rolex.org",
    "subtitleHost": "/-/media/rolex-org/",
    "publicURL": "/dist/rolex-org/",
    "graphQLEndpoint": "/api/rolex-org?sc_apikey={809331BB-4AAC-4B95-88AF-8D2F5B522D3C}",
    "graphQLEndpointPath": "/api/rolex-org",
    "graphQLDatabaseEndpoint": "/sitecore/api/graph/items/master?"
  }
}